setup.py
dsnd_distributions_1/Binomialdistribution.py
dsnd_distributions_1/Gaussiandistribution.py
dsnd_distributions_1/Generaldistribution.py
dsnd_distributions_1/__init__.py
dsnd_distributions_1.egg-info/PKG-INFO
dsnd_distributions_1.egg-info/SOURCES.txt
dsnd_distributions_1.egg-info/dependency_links.txt
dsnd_distributions_1.egg-info/not-zip-safe
dsnd_distributions_1.egg-info/top_level.txt