Metadata-Version: 2.1
Name: dsnd-distributions-1
Version: 1.0
Summary: Gaussian and Binomial distributions
Home-page: UNKNOWN
Author: Ahmad Sheikhzada
Author-email: 
License: UNKNOWN
Platform: UNKNOWN
